CreateBat/LICENSE
CreateBat/README.MD
CreateBat/__init__.py
CreateBat/requirements.txt
CreateBat/thirdparty.json
CreateBat-0.21.dist-info/LICENSE.rst
CreateBat-0.21.dist-info/METADATA
CreateBat-0.21.dist-info/WHEEL
CreateBat-0.21.dist-info/top_level.txt
CreateBat-0.21.dist-info/RECORD
